README.md
pyproject.toml
setup.py
totemlib/__init__.py
totemlib.egg-info/PKG-INFO
totemlib.egg-info/SOURCES.txt
totemlib.egg-info/dependency_links.txt
totemlib.egg-info/requires.txt
totemlib.egg-info/top_level.txt
totemlib/data/__init__.py
totemlib/data/transform.py
totemlib/security/__init__.py
totemlib/security/validations.py
totemlib/utils/__init__.py
totemlib/utils/logger.py
totemlib/utils/privproperties.py